simulate_user/__init__.py
simulate_user/admin.py
simulate_user/app_settings.py
simulate_user/apps.py
simulate_user/checks.py
simulate_user/context_processors.py
simulate_user/forms.py
simulate_user/middleware.py
simulate_user/models.py
simulate_user/signals.py
simulate_user/tests.py
simulate_user/urls.py
simulate_user/utils.py
simulate_user/views.py
simulate_user/migrations/0001_initial.py
simulate_user/migrations/__init__.py
simulate_user/static/simulate_user/css/styles.css
simulate_user/static/simulate_user/js/main.js
simulate_user/templates/simulate_user/simulate_user_base.html
simulate_user/templates/simulate_user/simulation_email.html
simulate_user/templates/simulate_user/simulation_email.txt
simulate_user/templates/simulate_user/simulation_email_subject.txt
simulate_user/templatetags/__init__.py
simulate_user/templatetags/private_tags.py
django_simulate_user-1.4.dist-info/LICENSE
django_simulate_user-1.4.dist-info/METADATA
django_simulate_user-1.4.dist-info/WHEEL
django_simulate_user-1.4.dist-info/top_level.txt
django_simulate_user-1.4.dist-info/RECORD
